anteml/__init__.py
anteml/attributes.py
anteml/elements.py
anteml/entities.py
anteml/errors.py
anteml/parser.py
AnTeML-0.1.4.dist-info/LICENSE
AnTeML-0.1.4.dist-info/METADATA
AnTeML-0.1.4.dist-info/WHEEL
AnTeML-0.1.4.dist-info/top_level.txt
AnTeML-0.1.4.dist-info/RECORD
