Metadata-Version: 2.1
Name: AnTeML
Version: 0.1.4
Summary: A stack-based HTML-like mini-language for encoding text with ANSI X3.64 Control Sequences
Home-page: https://github.com/thatfloflo/anteml
Author: Florian Breit
Author-email: florian@florian.me.uk
Project-URL: Bug Tracker, https://github.com/thatfloflo/anteml/issues
Classifier: Development Status :: 3 - Alpha
Classifier: Environment :: Console
Classifier: Programming Language :: Python :: 3
Classifier: Programming Language :: Python :: 3.10
Classifier: License :: OSI Approved :: GNU Lesser General Public License v3 (LGPLv3)
Classifier: Operating System :: OS Independent
Classifier: Topic :: Software Development :: Libraries
Classifier: Topic :: Software Development :: User Interfaces
Classifier: Topic :: Terminals
Classifier: Intended Audience :: Developers
Requires-Python: >=3.10
License-File: LICENSE
